[{"HOSTNAME": "vpn973222932.opengw.net", "LOCATION": "Bangladesh", "PING": "37 ms", "PORT": 995, "UPTIME": "11 days"}, {"HOSTNAME": "v-dot-pn-dus1.opengw.net", "LOCATION": "Germany", "PING": "3 ms", "PORT": 443, "UPTIME": "89 days"}, {"HOSTNAME": "public-vpn-210.opengw.net", "LOCATION": "Japan", "PING": "20 ms", "PORT": 443, "UPTIME": "1 days"}, {"HOSTNAME": "vpn553895099.opengw.net", "LOCATION": "Japan", "PING": "28 ms", "PORT": 1607, "UPTIME": "2 days"}, {"HOSTNAME": "vpn356090981.opengw.net", "LOCATION": "Japan", "PING": "5 ms", "PORT": 1709, "UPTIME": "1 days"}, {"HOSTNAME": "vpn490815878.opengw.net", "LOCATION": "Japan", "PING": "1 ms", "PORT": 1648, "UPTIME": "22 hours"}, {"HOSTNAME": "vpn790930670.opengw.net", "LOCATION": "Japan", "PING": "22 ms", "PORT": 1800, "UPTIME": "1 days"}, {"HOSTNAME": "vpn585445058.opengw.net", "LOCATION": "Japan", "PING": "5 ms", "PORT": 1571, "UPTIME": "16 hours"}, {"HOSTNAME": "vpn913650738.opengw.net", "LOCATION": "Japan", "PING": "27 ms", "PORT": 1512, "UPTIME": "19 hours"}, {"HOSTNAME": "public-vpn-206.opengw.net", "LOCATION": "Japan", "PING": "11 ms", "PORT": 443, "UPTIME": "32 days"}, {"HOSTNAME": "kozakura1234.opengw.net", "LOCATION": "Japan", "PING": "13 ms", "PORT": 443, "UPTIME": "2 hours"}, {"HOSTNAME": "vpn741087269.opengw.net", "LOCATION": "Japan", "PING": "2 ms", "PORT": 1479, "UPTIME": "2 hours"}, {"HOSTNAME": "vpn249464964.opengw.net", "LOCATION": "Japan", "PING": "5 ms", "PORT": 1739, "UPTIME": "2 hours"}, {"HOSTNAME": "vpn764493214.opengw.net", "LOCATION": "Japan", "PING": "18 ms", "PORT": 1597, "UPTIME": "2 hours"}, {"HOSTNAME": "vpn667296587.opengw.net", "LOCATION": "Japan", "PING": "17 ms", "PORT": 1646, "UPTIME": "0 mins"}, {"HOSTNAME": "vpn343424094.opengw.net", "LOCATION": "Japan", "PING": "14 ms", "PORT": 1333, "UPTIME": "2 hours"}, {"HOSTNAME": "vpn550493115.opengw.net", "LOCATION": "Japan", "PING": "4 ms", "PORT": 1797, "UPTIME": "0 mins"}, {"HOSTNAME": "vpn525453848.opengw.net", "LOCATION": "Japan", "PING": "11 ms", "PORT": 1868, "UPTIME": "0 mins"}, {"HOSTNAME": "vpn186634887.opengw.net", "LOCATION": "Japan", "PING": "29 ms", "PORT": 1813, "UPTIME": "3 days"}, {"HOSTNAME": "public-vpn-97.opengw.net", "LOCATION": "Japan", "PING": "17 ms", "PORT": 443, "UPTIME": "68 days"}, {"HOSTNAME": "public-vpn-107.opengw.net", "LOCATION": "Japan", "PING": "11 ms", "PORT": 443, "UPTIME": "109 days"}, {"HOSTNAME": "vpn790127243.opengw.net", "LOCATION": "Japan", "PING": "2 ms", "PORT": 1844, "UPTIME": "9 days"}, {"HOSTNAME": "public-vpn-209.opengw.net", "LOCATION": "Japan", "PING": "16 ms", "PORT": 443, "UPTIME": "151 days"}, {"HOSTNAME": "public-vpn-221.opengw.net", "LOCATION": "Japan", "PING": "18 ms", "PORT": 443, "UPTIME": "90 days"}, {"HOSTNAME": "public-vpn-229.opengw.net", "LOCATION": "Japan", "PING": "16 ms", "PORT": 443, "UPTIME": "187 days"}, {"HOSTNAME": "public-vpn-82.opengw.net", "LOCATION": "Japan", "PING": "8 ms", "PORT": 443, "UPTIME": "284 days"}, {"HOSTNAME": "public-vpn-154.opengw.net", "LOCATION": "Japan", "PING": "11 ms", "PORT": 443, "UPTIME": "116 days"}, {"HOSTNAME": "public-vpn-46.opengw.net", "LOCATION": "Japan", "PING": "23 ms", "PORT": 443, "UPTIME": "283 days"}, {"HOSTNAME": "public-vpn-66.opengw.net", "LOCATION": "Japan", "PING": "14 ms", "PORT": 443, "UPTIME": "123 days"}, {"HOSTNAME": "public-vpn-201.opengw.net", "LOCATION": "Japan", "PING": "19 ms", "PORT": 443, "UPTIME": "83 days"}, {"HOSTNAME": "public-vpn-113.opengw.net", "LOCATION": "Japan", "PING": "9 ms", "PORT": 443, "UPTIME": "23 days"}, {"HOSTNAME": "public-vpn-87.opengw.net", "LOCATION": "Japan", "PING": "15 ms", "PORT": 443, "UPTIME": "12 days"}, {"HOSTNAME": "public-vpn-236.opengw.net", "LOCATION": "Japan", "PING": "21 ms", "PORT": 443, "UPTIME": "14 days"}, {"HOSTNAME": "public-vpn-128.opengw.net", "LOCATION": "Japan", "PING": "17 ms", "PORT": 443, "UPTIME": "9 days"}, {"HOSTNAME": "vpn193195706.opengw.net", "LOCATION": "Japan", "PING": "17 ms", "PORT": 995, "UPTIME": "2 hours"}, {"HOSTNAME": "vpn377910956.opengw.net", "LOCATION": "Japan", "PING": "23 ms", "PORT": 1727, "UPTIME": "30 days"}, {"HOSTNAME": "vpn623603296.opengw.net", "LOCATION": "Republic of Korea", "PING": "29 ms", "PORT": 995, "UPTIME": "0 mins"}, {"HOSTNAME": "vpn169971623.opengw.net", "LOCATION": "Republic of Korea", "PING": "25 ms", "PORT": 995, "UPTIME": "2 hours"}, {"HOSTNAME": "vpn979676058.opengw.net", "LOCATION": "Republic of Korea", "PING": "30 ms", "PORT": 1611, "UPTIME": "0 mins"}, {"HOSTNAME": "vpn605045242.opengw.net", "LOCATION": "Republic of Korea", "PING": "31 ms", "PORT": 995, "UPTIME": "2 hours"}, {"HOSTNAME": "vpn184159088.opengw.net", "LOCATION": "Republic of Korea", "PING": "37 ms", "PORT": 1952, "UPTIME": "2 hours"}, {"HOSTNAME": "vpn436003477.opengw.net", "LOCATION": "Republic of Korea", "PING": "28 ms", "PORT": 995, "UPTIME": "2 hours"}, {"HOSTNAME": "vpn946091596.opengw.net", "LOCATION": "Republic of Korea", "PING": "32 ms", "PORT": 995, "UPTIME": "0 mins"}, {"HOSTNAME": "vpn665726518.opengw.net", "LOCATION": "Republic of Korea", "PING": "37 ms", "PORT": 995, "UPTIME": "2 hours"}, {"HOSTNAME": "vpn460701713.opengw.net", "LOCATION": "Republic of Korea", "PING": "28 ms", "PORT": 1404, "UPTIME": "13 days"}, {"HOSTNAME": "vpn580390840.opengw.net", "LOCATION": "Republic of Korea", "PING": "29 ms", "PORT": 1902, "UPTIME": "2 hours"}, {"HOSTNAME": "vpn164136850.opengw.net", "LOCATION": "Republic of Korea", "PING": "36 ms", "PORT": 1528, "UPTIME": "2 hours"}, {"HOSTNAME": "vpn638037739.opengw.net", "LOCATION": "Republic of Korea", "PING": "32 ms", "PORT": 995, "UPTIME": "2 hours"}, {"HOSTNAME": "vpn843315292.opengw.net", "LOCATION": "Republic of Korea", "PING": "36 ms", "PORT": 995, "UPTIME": "0 mins"}, {"HOSTNAME": "vpn849751823.opengw.net", "LOCATION": "Republic of Korea", "PING": "33 ms", "PORT": 995, "UPTIME": "2 hours"}, {"HOSTNAME": "vpn114329677.opengw.net", "LOCATION": "Republic of Korea", "PING": "33 ms", "PORT": 1423, "UPTIME": "2 hours"}, {"HOSTNAME": "vpn987015307.opengw.net", "LOCATION": "Republic of Korea", "PING": "46 ms", "PORT": 1941, "UPTIME": "2 hours"}, {"HOSTNAME": "vpn915220325.opengw.net", "LOCATION": "Republic of Korea", "PING": "61 ms", "PORT": 1264, "UPTIME": "2 hours"}, {"HOSTNAME": "vpn672798768.opengw.net", "LOCATION": "Republic of Korea", "PING": "27 ms", "PORT": 1647, "UPTIME": "0 mins"}, {"HOSTNAME": "vpn870312195.opengw.net", "LOCATION": "Republic of Korea", "PING": "37 ms", "PORT": 1768, "UPTIME": "2 days"}, {"HOSTNAME": "vpn262580528.opengw.net", "LOCATION": "Republic of Korea", "PING": "36 ms", "PORT": 1263, "UPTIME": "40 days"}, {"HOSTNAME": "vpn521751774.opengw.net", "LOCATION": "Republic of Korea", "PING": "27 ms", "PORT": 995, "UPTIME": "16 days"}, {"HOSTNAME": "vpn277478068.opengw.net", "LOCATION": "Republic of Korea", "PING": "36 ms", "PORT": 995, "UPTIME": "14 days"}, {"HOSTNAME": "vpn510487970.opengw.net", "LOCATION": "Republic of Korea", "PING": "37 ms", "PORT": 1555, "UPTIME": "2 days"}, {"HOSTNAME": "vpn247371292.opengw.net", "LOCATION": "Republic of Korea", "PING": "31 ms", "PORT": 995, "UPTIME": "1 days"}, {"HOSTNAME": "vpn382905705.opengw.net", "LOCATION": "Republic of Korea", "PING": "27 ms", "PORT": 1379, "UPTIME": "1 days"}, {"HOSTNAME": "vpn820228972.opengw.net", "LOCATION": "Republic of Korea", "PING": "39 ms", "PORT": 1375, "UPTIME": "1 days"}, {"HOSTNAME": "vpn157781468.opengw.net", "LOCATION": "Republic of Korea", "PING": "31 ms", "PORT": 1731, "UPTIME": "1 days"}, {"HOSTNAME": "vpn545865087.opengw.net", "LOCATION": "Republic of Korea", "PING": "27 ms", "PORT": 1913, "UPTIME": "16 hours"}, {"HOSTNAME": "vpn500604901.opengw.net", "LOCATION": "Republic of Korea", "PING": "38 ms", "PORT": 1896, "UPTIME": "3 days"}, {"HOSTNAME": "vpn722327931.opengw.net", "LOCATION": "Republic of Korea", "PING": "31 ms", "PORT": 995, "UPTIME": "19 hours"}, {"HOSTNAME": "vpn834220033.opengw.net", "LOCATION": "Republic of Korea", "PING": "37 ms", "PORT": 995, "UPTIME": "89 days"}, {"HOSTNAME": "vpn745373450.opengw.net", "LOCATION": "Republic of Korea", "PING": "25 ms", "PORT": 1381, "UPTIME": "0 mins"}, {"HOSTNAME": "vpn653717896.opengw.net", "LOCATION": "Republic of Korea", "PING": "46 ms", "PORT": 1894, "UPTIME": "1 days"}, {"HOSTNAME": "vpn119967238.opengw.net", "LOCATION": "Republic of Korea", "PING": "31 ms", "PORT": 995, "UPTIME": "5 days"}, {"HOSTNAME": "vpn763810031.opengw.net", "LOCATION": "Republic of Korea", "PING": "69 ms", "PORT": 1628, "UPTIME": "22 hours"}, {"HOSTNAME": "vpn157753729.opengw.net", "LOCATION": "Republic of Korea", "PING": "31 ms", "PORT": 1699, "UPTIME": "2 hours"}, {"HOSTNAME": "vpn637545575.opengw.net", "LOCATION": "Republic of Korea", "PING": "46 ms", "PORT": 1644, "UPTIME": "89 days"}, {"HOSTNAME": "vpn421199780.opengw.net", "LOCATION": "Republic of Korea", "PING": "32 ms", "PORT": 1748, "UPTIME": "2 hours"}, {"HOSTNAME": "vpn704294482.opengw.net", "LOCATION": "Romania", "PING": "1 ms", "PORT": 443, "UPTIME": "89 days"}, {"HOSTNAME": "vpn551989303.opengw.net", "LOCATION": "Romania", "PING": "1 ms", "PORT": 443, "UPTIME": "89 days"}, {"HOSTNAME": "vpn227012930.opengw.net", "LOCATION": "Russian Federation", "PING": "59 ms", "PORT": 1857, "UPTIME": "0 mins"}, {"HOSTNAME": "vpn822230190.opengw.net", "LOCATION": "Russian Federation", "PING": "130 ms", "PORT": 1639, "UPTIME": "2 hours"}, {"HOSTNAME": "vpn164083621.opengw.net", "LOCATION": "Thailand", "PING": "25 ms", "PORT": 1623, "UPTIME": "2 hours"}, {"HOSTNAME": "vpn194705305.opengw.net", "LOCATION": "Thailand", "PING": "38 ms", "PORT": 1205, "UPTIME": "22 hours"}, {"HOSTNAME": "vpn788545108.opengw.net", "LOCATION": "United States", "PING": "33 ms", "PORT": 1749, "UPTIME": "2 hours"}, {"HOSTNAME": "vpn191650407.opengw.net", "LOCATION": "United States", "PING": "37 ms", "PORT": 1726, "UPTIME": "16 hours"}, {"HOSTNAME": "vpn226322858.opengw.net", "LOCATION": "United States", "PING": "47 ms", "PORT": 1677, "UPTIME": "19 hours"}, {"HOSTNAME": "vpn887309670.opengw.net", "LOCATION": "Viet Nam", "PING": "33 ms", "PORT": 1644, "UPTIME": "4 days"}, {"HOSTNAME": "vpn256674926.opengw.net", "LOCATION": "Viet Nam", "PING": "27 ms", "PORT": 1782, "UPTIME": "2 hours"}]