[{"HOSTNAME": "vpn287196162.opengw.net", "LOCATION": "Cambodia", "PING": "63 ms", "PORT": 1994, "UPTIME": "3 hours"}, {"HOSTNAME": "vpn306067765.opengw.net", "LOCATION": "Cambodia", "PING": "37 ms", "PORT": 1979, "UPTIME": "0 mins"}, {"HOSTNAME": "vpn161672716.opengw.net", "LOCATION": "Canada", "PING": "26 ms", "PORT": 1856, "UPTIME": "10 days"}, {"HOSTNAME": "vpn185879306.opengw.net", "LOCATION": "Canada", "PING": "18 ms", "PORT": 1894, "UPTIME": "19 hours"}, {"HOSTNAME": "_unregistered_vpn341479952.opengw.net", "LOCATION": "China", "PING": "37 ms", "PORT": 992, "UPTIME": "14 days"}, {"HOSTNAME": "vpn791614438.opengw.net", "LOCATION": "Indonesia", "PING": "33 ms", "PORT": 1544, "UPTIME": "19 hours"}, {"HOSTNAME": "public-vpn-82.opengw.net", "LOCATION": "Japan", "PING": "14 ms", "PORT": 443, "UPTIME": "17 days"}, {"HOSTNAME": "public-vpn-98.opengw.net", "LOCATION": "Japan", "PING": "17 ms", "PORT": 443, "UPTIME": "17 days"}, {"HOSTNAME": "vpn113011305.opengw.net", "LOCATION": "Japan", "PING": "31 ms", "PORT": 1300, "UPTIME": "5 days"}, {"HOSTNAME": "vpn134589412.opengw.net", "LOCATION": "Japan", "PING": "20 ms", "PORT": 1319, "UPTIME": "1 days"}, {"HOSTNAME": "vpn860432976.opengw.net", "LOCATION": "Japan", "PING": "4 ms", "PORT": 1677, "UPTIME": "7 hours"}, {"HOSTNAME": "vpn220080326.opengw.net", "LOCATION": "Japan", "PING": "8 ms", "PORT": 1729, "UPTIME": "7 hours"}, {"HOSTNAME": "vpn127354464.opengw.net", "LOCATION": "Japan", "PING": "3 ms", "PORT": 1629, "UPTIME": "3 hours"}, {"HOSTNAME": "vpn170238284.opengw.net", "LOCATION": "Japan", "PING": "5 ms", "PORT": 1570, "UPTIME": "7 hours"}, {"HOSTNAME": "vpn872587913.opengw.net", "LOCATION": "Japan", "PING": "5 ms", "PORT": 1495, "UPTIME": "7 hours"}, {"HOSTNAME": "vpn724393492.opengw.net", "LOCATION": "Japan", "PING": "243 ms", "PORT": 1911, "UPTIME": "48 days"}, {"HOSTNAME": "vpn123623143.opengw.net", "LOCATION": "Japan", "PING": "12 ms", "PORT": 1556, "UPTIME": "0 mins"}, {"HOSTNAME": "vpn999988488.opengw.net", "LOCATION": "Japan", "PING": "17 ms", "PORT": 1572, "UPTIME": "0 mins"}, {"HOSTNAME": "vpn301766231.opengw.net", "LOCATION": "Japan", "PING": "2 ms", "PORT": 1370, "UPTIME": "0 mins"}, {"HOSTNAME": "vpn878147665.opengw.net", "LOCATION": "Japan", "PING": "8 ms", "PORT": 1863, "UPTIME": "0 mins"}, {"HOSTNAME": "vpn300879048.opengw.net", "LOCATION": "Japan", "PING": "5 ms", "PORT": 1224, "UPTIME": "0 mins"}, {"HOSTNAME": "vpn360714885.opengw.net", "LOCATION": "Japan", "PING": "6 ms", "PORT": 1854, "UPTIME": "0 mins"}, {"HOSTNAME": "vpn103139653.opengw.net", "LOCATION": "Japan", "PING": "16 ms", "PORT": 1439, "UPTIME": "0 mins"}, {"HOSTNAME": "vpn516290961.opengw.net", "LOCATION": "Japan", "PING": "36 ms", "PORT": 1479, "UPTIME": "3 hours"}, {"HOSTNAME": "vpn871762545.opengw.net", "LOCATION": "Japan", "PING": "9 ms", "PORT": 1453, "UPTIME": "1 days"}, {"HOSTNAME": "vpn248855312.opengw.net", "LOCATION": "Japan", "PING": "7 ms", "PORT": 1243, "UPTIME": "7 hours"}, {"HOSTNAME": "public-vpn-209.opengw.net", "LOCATION": "Japan", "PING": "30 ms", "PORT": 443, "UPTIME": "17 days"}, {"HOSTNAME": "vpn511818512.opengw.net", "LOCATION": "Japan", "PING": "2 ms", "PORT": 1613, "UPTIME": "5 days"}, {"HOSTNAME": "public-vpn-201.opengw.net", "LOCATION": "Japan", "PING": "28 ms", "PORT": 443, "UPTIME": "17 days"}, {"HOSTNAME": "public-vpn-186.opengw.net", "LOCATION": "Japan", "PING": "12 ms", "PORT": 443, "UPTIME": "17 days"}, {"HOSTNAME": "public-vpn-68.opengw.net", "LOCATION": "Japan", "PING": "12 ms", "PORT": 443, "UPTIME": "17 days"}, {"HOSTNAME": "public-vpn-221.opengw.net", "LOCATION": "Japan", "PING": "22 ms", "PORT": 443, "UPTIME": "17 days"}, {"HOSTNAME": "public-vpn-139.opengw.net", "LOCATION": "Japan", "PING": "10 ms", "PORT": 443, "UPTIME": "17 days"}, {"HOSTNAME": "vpn399916504.opengw.net", "LOCATION": "Japan", "PING": "20 ms", "PORT": 1755, "UPTIME": "12 days"}, {"HOSTNAME": "vpn961553468.opengw.net", "LOCATION": "Japan", "PING": "5 ms", "PORT": 1218, "UPTIME": "12 days"}, {"HOSTNAME": "public-vpn-105.opengw.net", "LOCATION": "Japan", "PING": "23 ms", "PORT": 443, "UPTIME": "17 days"}, {"HOSTNAME": "public-vpn-109.opengw.net", "LOCATION": "Japan", "PING": "14 ms", "PORT": 443, "UPTIME": "17 days"}, {"HOSTNAME": "public-vpn-48.opengw.net", "LOCATION": "Japan", "PING": "24 ms", "PORT": 443, "UPTIME": "17 days"}, {"HOSTNAME": "vpn245611782.opengw.net", "LOCATION": "Japan", "PING": "11 ms", "PORT": 1972, "UPTIME": "6 days"}, {"HOSTNAME": "vpn274449287.opengw.net", "LOCATION": "Japan", "PING": "33 ms", "PORT": 1694, "UPTIME": "8 days"}, {"HOSTNAME": "public-vpn-237.opengw.net", "LOCATION": "Japan", "PING": "17 ms", "PORT": 443, "UPTIME": "17 days"}, {"HOSTNAME": "public-vpn-231.opengw.net", "LOCATION": "Japan", "PING": "18 ms", "PORT": 443, "UPTIME": "17 days"}, {"HOSTNAME": "vpn529704301.opengw.net", "LOCATION": "Republic of Korea", "PING": "32 ms", "PORT": 1433, "UPTIME": "0 mins"}, {"HOSTNAME": "vpn710866893.opengw.net", "LOCATION": "Republic of Korea", "PING": "27 ms", "PORT": 443, "UPTIME": "0 mins"}, {"HOSTNAME": "vpn739780220.opengw.net", "LOCATION": "Republic of Korea", "PING": "33 ms", "PORT": 1721, "UPTIME": "3 hours"}, {"HOSTNAME": "vpn211860804.opengw.net", "LOCATION": "Republic of Korea", "PING": "30 ms", "PORT": 995, "UPTIME": "7 hours"}, {"HOSTNAME": "vpn801893282.opengw.net", "LOCATION": "Republic of Korea", "PING": "37 ms", "PORT": 995, "UPTIME": "0 mins"}, {"HOSTNAME": "vpn733746384.opengw.net", "LOCATION": "Republic of Korea", "PING": "35 ms", "PORT": 995, "UPTIME": "0 mins"}, {"HOSTNAME": "vpn656993625.opengw.net", "LOCATION": "Republic of Korea", "PING": "32 ms", "PORT": 1979, "UPTIME": "0 mins"}, {"HOSTNAME": "vpn634411157.opengw.net", "LOCATION": "Republic of Korea", "PING": "33 ms", "PORT": 1392, "UPTIME": "0 mins"}, {"HOSTNAME": "vpn806547151.opengw.net", "LOCATION": "Republic of Korea", "PING": "32 ms", "PORT": 1341, "UPTIME": "3 hours"}, {"HOSTNAME": "vpn670792139.opengw.net", "LOCATION": "Republic of Korea", "PING": "31 ms", "PORT": 995, "UPTIME": "0 mins"}, {"HOSTNAME": "vpn419223159.opengw.net", "LOCATION": "Republic of Korea", "PING": "29 ms", "PORT": 995, "UPTIME": "0 mins"}, {"HOSTNAME": "vpn965997853.opengw.net", "LOCATION": "Republic of Korea", "PING": "45 ms", "PORT": 995, "UPTIME": "3 hours"}, {"HOSTNAME": "vpn105746911.opengw.net", "LOCATION": "Republic of Korea", "PING": "28 ms", "PORT": 995, "UPTIME": "0 mins"}, {"HOSTNAME": "vpn731747493.opengw.net", "LOCATION": "Republic of Korea", "PING": "35 ms", "PORT": 1537, "UPTIME": "0 mins"}, {"HOSTNAME": "vpn676824087.opengw.net", "LOCATION": "Republic of Korea", "PING": "34 ms", "PORT": 995, "UPTIME": "7 hours"}, {"HOSTNAME": "vpn468596368.opengw.net", "LOCATION": "Republic of Korea", "PING": "35 ms", "PORT": 1995, "UPTIME": "0 mins"}, {"HOSTNAME": "vpn594845714.opengw.net", "LOCATION": "Republic of Korea", "PING": "32 ms", "PORT": 995, "UPTIME": "0 mins"}, {"HOSTNAME": "vpn361748903.opengw.net", "LOCATION": "Republic of Korea", "PING": "32 ms", "PORT": 1826, "UPTIME": "0 mins"}, {"HOSTNAME": "vpn164920285.opengw.net", "LOCATION": "Republic of Korea", "PING": "27 ms", "PORT": 995, "UPTIME": "3 days"}, {"HOSTNAME": "vpn243272299.opengw.net", "LOCATION": "Republic of Korea", "PING": "28 ms", "PORT": 1520, "UPTIME": "7 hours"}, {"HOSTNAME": "vpn377813625.opengw.net", "LOCATION": "Republic of Korea", "PING": "33 ms", "PORT": 1545, "UPTIME": "3 hours"}, {"HOSTNAME": "vpn743907007.opengw.net", "LOCATION": "Republic of Korea", "PING": "36 ms", "PORT": 1219, "UPTIME": "7 hours"}, {"HOSTNAME": "vpn299013327.opengw.net", "LOCATION": "Republic of Korea", "PING": "27 ms", "PORT": 995, "UPTIME": "3 days"}, {"HOSTNAME": "vpn424595374.opengw.net", "LOCATION": "Republic of Korea", "PING": "31 ms", "PORT": 995, "UPTIME": "4 days"}, {"HOSTNAME": "vpn680675631.opengw.net", "LOCATION": "Republic of Korea", "PING": "35 ms", "PORT": 443, "UPTIME": "2 days"}, {"HOSTNAME": "vpn362882822.opengw.net", "LOCATION": "Republic of Korea", "PING": "27 ms", "PORT": 1861, "UPTIME": "2 days"}, {"HOSTNAME": "vpn868961782.opengw.net", "LOCATION": "Republic of Korea", "PING": "35 ms", "PORT": 995, "UPTIME": "2 days"}, {"HOSTNAME": "vpn991761633.opengw.net", "LOCATION": "Republic of Korea", "PING": "36 ms", "PORT": 1544, "UPTIME": "1 days"}, {"HOSTNAME": "vpn218865886.opengw.net", "LOCATION": "Republic of Korea", "PING": "29 ms", "PORT": 1228, "UPTIME": "1 days"}, {"HOSTNAME": "vpn739226409.opengw.net", "LOCATION": "Republic of Korea", "PING": "31 ms", "PORT": 1600, "UPTIME": "1 days"}, {"HOSTNAME": "vpn638542523.opengw.net", "LOCATION": "Republic of Korea", "PING": "39 ms", "PORT": 1255, "UPTIME": "1 days"}, {"HOSTNAME": "vpn562214874.opengw.net", "LOCATION": "Republic of Korea", "PING": "35 ms", "PORT": 995, "UPTIME": "1 days"}, {"HOSTNAME": "vpn482635064.opengw.net", "LOCATION": "Republic of Korea", "PING": "34 ms", "PORT": 1762, "UPTIME": "23 hours"}, {"HOSTNAME": "vpn302138817.opengw.net", "LOCATION": "Republic of Korea", "PING": "31 ms", "PORT": 995, "UPTIME": "16 days"}, {"HOSTNAME": "vpn231039216.opengw.net", "LOCATION": "Republic of Korea", "PING": "35 ms", "PORT": 995, "UPTIME": "48 days"}, {"HOSTNAME": "vpn891318488.opengw.net", "LOCATION": "Republic of Korea", "PING": "37 ms", "PORT": 995, "UPTIME": "23 hours"}, {"HOSTNAME": "vpn267531295.opengw.net", "LOCATION": "Republic of Korea", "PING": "27 ms", "PORT": 995, "UPTIME": "7 hours"}, {"HOSTNAME": "vpn667025631.opengw.net", "LOCATION": "Republic of Korea", "PING": "30 ms", "PORT": 995, "UPTIME": "7 hours"}, {"HOSTNAME": "vpn860172447.opengw.net", "LOCATION": "Republic of Korea", "PING": "33 ms", "PORT": 995, "UPTIME": "8 days"}, {"HOSTNAME": "vpn408004478.opengw.net", "LOCATION": "Republic of Korea", "PING": "30 ms", "PORT": 995, "UPTIME": "7 hours"}, {"HOSTNAME": "vpn992255863.opengw.net", "LOCATION": "Russian Federation", "PING": "125 ms", "PORT": 1271, "UPTIME": "0 mins"}, {"HOSTNAME": "vpn496291485.opengw.net", "LOCATION": "Thailand", "PING": "31 ms", "PORT": 1696, "UPTIME": "7 hours"}, {"HOSTNAME": "vpn208589546.opengw.net", "LOCATION": "United Kingdom", "PING": "23 ms", "PORT": 1327, "UPTIME": "0 mins"}]