[{"HOSTNAME": "vpn953219231.opengw.net", "LOCATION": "Indonesia", "PING": "31 ms", "PORT": 1511, "UPTIME": "0 mins"}, {"HOSTNAME": "vpn855515524.opengw.net", "LOCATION": "Japan", "PING": "8 ms", "PORT": 1688, "UPTIME": "13 days"}, {"HOSTNAME": "vpn720348622.opengw.net", "LOCATION": "Japan", "PING": "4 ms", "PORT": 1451, "UPTIME": "0 mins"}, {"HOSTNAME": "vpn431575930.opengw.net", "LOCATION": "Japan", "PING": "8 ms", "PORT": 1330, "UPTIME": "20 hours"}, {"HOSTNAME": "vpn128907850.opengw.net", "LOCATION": "Japan", "PING": "4 ms", "PORT": 1958, "UPTIME": "8 hours"}, {"HOSTNAME": "vpn460710060.opengw.net", "LOCATION": "Japan", "PING": "4 ms", "PORT": 1352, "UPTIME": "20 hours"}, {"HOSTNAME": "vpn442667024.opengw.net", "LOCATION": "Japan", "PING": "8 ms", "PORT": 1657, "UPTIME": "8 hours"}, {"HOSTNAME": "vpn295363920.opengw.net", "LOCATION": "Japan", "PING": "21 ms", "PORT": 1985, "UPTIME": "2 hours"}, {"HOSTNAME": "vpn773098820.opengw.net", "LOCATION": "Japan", "PING": "9 ms", "PORT": 1697, "UPTIME": "5 hours"}, {"HOSTNAME": "vpn777891891.opengw.net", "LOCATION": "Japan", "PING": "2 ms", "PORT": 1327, "UPTIME": "8 hours"}, {"HOSTNAME": "vpn988000718.opengw.net", "LOCATION": "Japan", "PING": "11 ms", "PORT": 1318, "UPTIME": "2 hours"}, {"HOSTNAME": "vpn420004139.opengw.net", "LOCATION": "Japan", "PING": "10 ms", "PORT": 1842, "UPTIME": "0 mins"}, {"HOSTNAME": "vpn343026611.opengw.net", "LOCATION": "Japan", "PING": "6 ms", "PORT": 1292, "UPTIME": "0 mins"}, {"HOSTNAME": "vpn621977898.opengw.net", "LOCATION": "Japan", "PING": "19 ms", "PORT": 1736, "UPTIME": "2 hours"}, {"HOSTNAME": "public-vpn-210.opengw.net", "LOCATION": "Japan", "PING": "15 ms", "PORT": 443, "UPTIME": "9 hours"}, {"HOSTNAME": "vpn510327043.opengw.net", "LOCATION": "Japan", "PING": "9 ms", "PORT": 1354, "UPTIME": "5 hours"}, {"HOSTNAME": "vpn392851914.opengw.net", "LOCATION": "Japan", "PING": "3 ms", "PORT": 1764, "UPTIME": "0 mins"}, {"HOSTNAME": "vpn900950806.opengw.net", "LOCATION": "Japan", "PING": "12 ms", "PORT": 1346, "UPTIME": "2 hours"}, {"HOSTNAME": "vpn978055064.opengw.net", "LOCATION": "Japan", "PING": "11 ms", "PORT": 1571, "UPTIME": "0 mins"}, {"HOSTNAME": "vpn556696341.opengw.net", "LOCATION": "Japan", "PING": "9 ms", "PORT": 1606, "UPTIME": "0 mins"}, {"HOSTNAME": "vpn508560885.opengw.net", "LOCATION": "Japan", "PING": "11 ms", "PORT": 1882, "UPTIME": "2 hours"}, {"HOSTNAME": "vpn249418964.opengw.net", "LOCATION": "Japan", "PING": "18 ms", "PORT": 1641, "UPTIME": "0 mins"}, {"HOSTNAME": "vpn293151675.opengw.net", "LOCATION": "Japan", "PING": "12 ms", "PORT": 1618, "UPTIME": "0 mins"}, {"HOSTNAME": "vpn794688249.opengw.net", "LOCATION": "Japan", "PING": "7 ms", "PORT": 1620, "UPTIME": "0 mins"}, {"HOSTNAME": "vpn202024260.opengw.net", "LOCATION": "Japan", "PING": "6 ms", "PORT": 1545, "UPTIME": "5 hours"}, {"HOSTNAME": "vpn261291707.opengw.net", "LOCATION": "Japan", "PING": "13 ms", "PORT": 1428, "UPTIME": "2 hours"}, {"HOSTNAME": "vpn628652255.opengw.net", "LOCATION": "Japan", "PING": "7 ms", "PORT": 1910, "UPTIME": "1 days"}, {"HOSTNAME": "vpn223857877.opengw.net", "LOCATION": "Japan", "PING": "18 ms", "PORT": 1754, "UPTIME": "1 days"}, {"HOSTNAME": "public-vpn-154.opengw.net", "LOCATION": "Japan", "PING": "22 ms", "PORT": 443, "UPTIME": "9 hours"}, {"HOSTNAME": "public-vpn-259.opengw.net", "LOCATION": "Japan", "PING": "11 ms", "PORT": 443, "UPTIME": "9 hours"}, {"HOSTNAME": "public-vpn-206.opengw.net", "LOCATION": "Japan", "PING": "9 ms", "PORT": 443, "UPTIME": "9 hours"}, {"HOSTNAME": "public-vpn-236.opengw.net", "LOCATION": "Japan", "PING": "25 ms", "PORT": 443, "UPTIME": "9 hours"}, {"HOSTNAME": "public-vpn-225.opengw.net", "LOCATION": "Japan", "PING": "8 ms", "PORT": 443, "UPTIME": "9 hours"}, {"HOSTNAME": "public-vpn-229.opengw.net", "LOCATION": "Japan", "PING": "8 ms", "PORT": 443, "UPTIME": "9 hours"}, {"HOSTNAME": "public-vpn-174.opengw.net", "LOCATION": "Japan", "PING": "22 ms", "PORT": 443, "UPTIME": "9 hours"}, {"HOSTNAME": "public-vpn-46.opengw.net", "LOCATION": "Japan", "PING": "12 ms", "PORT": 443, "UPTIME": "9 hours"}, {"HOSTNAME": "public-vpn-173.opengw.net", "LOCATION": "Japan", "PING": "11 ms", "PORT": 443, "UPTIME": "9 hours"}, {"HOSTNAME": "vpn783816894.opengw.net", "LOCATION": "Japan", "PING": "21 ms", "PORT": 1234, "UPTIME": "0 mins"}, {"HOSTNAME": "vpn159703190.opengw.net", "LOCATION": "Japan", "PING": "5 ms", "PORT": 1431, "UPTIME": "2 days"}, {"HOSTNAME": "vpn943399236.opengw.net", "LOCATION": "Japan", "PING": "5 ms", "PORT": 1459, "UPTIME": "1 days"}, {"HOSTNAME": "public-vpn-201.opengw.net", "LOCATION": "Japan", "PING": "14 ms", "PORT": 443, "UPTIME": "9 hours"}, {"HOSTNAME": "public-vpn-171.opengw.net", "LOCATION": "Japan", "PING": "30 ms", "PORT": 443, "UPTIME": "9 hours"}, {"HOSTNAME": "public-vpn-66.opengw.net", "LOCATION": "Japan", "PING": "9 ms", "PORT": 443, "UPTIME": "9 hours"}, {"HOSTNAME": "vpn211875763.opengw.net", "LOCATION": "Republic of Korea", "PING": "31 ms", "PORT": 1296, "UPTIME": "2 hours"}, {"HOSTNAME": "vpn602664119.opengw.net", "LOCATION": "Republic of Korea", "PING": "32 ms", "PORT": 1677, "UPTIME": "2 hours"}, {"HOSTNAME": "vpn867667390.opengw.net", "LOCATION": "Republic of Korea", "PING": "30 ms", "PORT": 995, "UPTIME": "2 hours"}, {"HOSTNAME": "vpn229127509.opengw.net", "LOCATION": "Republic of Korea", "PING": "31 ms", "PORT": 1648, "UPTIME": "8 hours"}, {"HOSTNAME": "vpn549528020.opengw.net", "LOCATION": "Republic of Korea", "PING": "34 ms", "PORT": 1609, "UPTIME": "5 hours"}, {"HOSTNAME": "vpn452200494.opengw.net", "LOCATION": "Republic of Korea", "PING": "25 ms", "PORT": 1983, "UPTIME": "0 mins"}, {"HOSTNAME": "vpn838556596.opengw.net", "LOCATION": "Republic of Korea", "PING": "31 ms", "PORT": 995, "UPTIME": "5 hours"}, {"HOSTNAME": "vpn610582094.opengw.net", "LOCATION": "Republic of Korea", "PING": "39 ms", "PORT": 1484, "UPTIME": "20 hours"}, {"HOSTNAME": "vpn710574944.opengw.net", "LOCATION": "Republic of Korea", "PING": "34 ms", "PORT": 1627, "UPTIME": "8 hours"}, {"HOSTNAME": "vpn502179981.opengw.net", "LOCATION": "Republic of Korea", "PING": "32 ms", "PORT": 995, "UPTIME": "5 hours"}, {"HOSTNAME": "vpn711898278.opengw.net", "LOCATION": "Republic of Korea", "PING": "25 ms", "PORT": 995, "UPTIME": "0 mins"}, {"HOSTNAME": "vpn996713702.opengw.net", "LOCATION": "Republic of Korea", "PING": "32 ms", "PORT": 995, "UPTIME": "0 mins"}, {"HOSTNAME": "vpn590672701.opengw.net", "LOCATION": "Republic of Korea", "PING": "27 ms", "PORT": 995, "UPTIME": "0 mins"}, {"HOSTNAME": "vpn565343842.opengw.net", "LOCATION": "Republic of Korea", "PING": "29 ms", "PORT": 1772, "UPTIME": "0 mins"}, {"HOSTNAME": "vpn951114320.opengw.net", "LOCATION": "Republic of Korea", "PING": "30 ms", "PORT": 1535, "UPTIME": "5 hours"}, {"HOSTNAME": "vpn784219240.opengw.net", "LOCATION": "Republic of Korea", "PING": "32 ms", "PORT": 1525, "UPTIME": "8 hours"}, {"HOSTNAME": "vpn162474067.opengw.net", "LOCATION": "Republic of Korea", "PING": "33 ms", "PORT": 1262, "UPTIME": "8 hours"}, {"HOSTNAME": "vpn197150017.opengw.net", "LOCATION": "Republic of Korea", "PING": "42 ms", "PORT": 1336, "UPTIME": "1 days"}, {"HOSTNAME": "vpn292461721.opengw.net", "LOCATION": "Republic of Korea", "PING": "22 ms", "PORT": 995, "UPTIME": "8 hours"}, {"HOSTNAME": "vpn499028102.opengw.net", "LOCATION": "Republic of Korea", "PING": "31 ms", "PORT": 995, "UPTIME": "1 days"}, {"HOSTNAME": "vpn331747366.opengw.net", "LOCATION": "Republic of Korea", "PING": "31 ms", "PORT": 995, "UPTIME": "26 days"}, {"HOSTNAME": "vpn934489145.opengw.net", "LOCATION": "Republic of Korea", "PING": "39 ms", "PORT": 1380, "UPTIME": "13 days"}, {"HOSTNAME": "vpn454031004.opengw.net", "LOCATION": "Republic of Korea", "PING": "29 ms", "PORT": 995, "UPTIME": "37 days"}, {"HOSTNAME": "vpn257282737.opengw.net", "LOCATION": "Republic of Korea", "PING": "29 ms", "PORT": 1226, "UPTIME": "11 days"}, {"HOSTNAME": "vpn736511371.opengw.net", "LOCATION": "Republic of Korea", "PING": "26 ms", "PORT": 1472, "UPTIME": "4 days"}, {"HOSTNAME": "vpn350737147.opengw.net", "LOCATION": "Republic of Korea", "PING": "-", "PORT": 1629, "UPTIME": "5 days"}, {"HOSTNAME": "vpn252471670.opengw.net", "LOCATION": "Republic of Korea", "PING": "22 ms", "PORT": 1822, "UPTIME": "8 hours"}, {"HOSTNAME": "vpn825158727.opengw.net", "LOCATION": "Republic of Korea", "PING": "32 ms", "PORT": 1375, "UPTIME": "1 days"}, {"HOSTNAME": "vpn952546144.opengw.net", "LOCATION": "Republic of Korea", "PING": "32 ms", "PORT": 1341, "UPTIME": "3 days"}, {"HOSTNAME": "vpn523238398.opengw.net", "LOCATION": "Republic of Korea", "PING": "28 ms", "PORT": 995, "UPTIME": "1 days"}, {"HOSTNAME": "vpn781100852.opengw.net", "LOCATION": "Republic of Korea", "PING": "27 ms", "PORT": 995, "UPTIME": "1 days"}, {"HOSTNAME": "vpn132492095.opengw.net", "LOCATION": "Republic of Korea", "PING": "31 ms", "PORT": 1310, "UPTIME": "1 days"}, {"HOSTNAME": "vpn715903134.opengw.net", "LOCATION": "Republic of Korea", "PING": "38 ms", "PORT": 1678, "UPTIME": "23 hours"}, {"HOSTNAME": "vpn444975756.opengw.net", "LOCATION": "Republic of Korea", "PING": "32 ms", "PORT": 995, "UPTIME": "36 days"}, {"HOSTNAME": "vpn285241260.opengw.net", "LOCATION": "Republic of Korea", "PING": "31 ms", "PORT": 1746, "UPTIME": "0 mins"}, {"HOSTNAME": "vpn227715037.opengw.net", "LOCATION": "Republic of Korea", "PING": "37 ms", "PORT": 1434, "UPTIME": "20 hours"}, {"HOSTNAME": "vpn729431378.opengw.net", "LOCATION": "Republic of Korea", "PING": "31 ms", "PORT": 1851, "UPTIME": "1 days"}, {"HOSTNAME": "vpn341466652.opengw.net", "LOCATION": "Republic of Korea", "PING": "29 ms", "PORT": 1432, "UPTIME": "20 hours"}, {"HOSTNAME": "vpn927186593.opengw.net", "LOCATION": "Republic of Korea", "PING": "40 ms", "PORT": 465, "UPTIME": "1 days"}, {"HOSTNAME": "vpn453327113.opengw.net", "LOCATION": "Romania", "PING": "1 ms", "PORT": 443, "UPTIME": "20 days"}, {"HOSTNAME": "tlt.opengw.net", "LOCATION": "Russian Federation", "PING": "74 ms", "PORT": 996, "UPTIME": "12 days"}, {"HOSTNAME": "vpn212759038.opengw.net", "LOCATION": "Spain", "PING": "30 ms", "PORT": 995, "UPTIME": "0 mins"}]